[
	{
		"Name": "Max Agility Actions {2}/{0}",
		"Type": "Complication",
		"Tip": "Do not perform more than {0} agility actions in total.",
		"Group": "Action",
		"Difficulty": "High",
		"AgilityStart": {
			"Count": {
				"Random": [3, 5, 10, 15, 20]
			}
		}
	},
	{
		"Name": "Max Shots Fired {2}/{0}",
		"Type": "Complication",
		"Tip": "Do not fire more than {0} shots from any kind of gun.",
		"Group": "Action",
		"Difficulty": "High",
		"PlayerShot": {
			"Count": {
				"Random": [3, 5, 10, 15, 20]
			}
		}
	},
	{
		"Disabled": true,
		"Name": "No Assault Rifle Shots",
		"Type": "Complication",
		"Tip": "Do not fire any shots using an assault rifle.",
		"Group": "Action",
		"Difficulty": "Medium",
		"PlayerShot": {
			"WeaponCategory": "Rifle"
		}
	},
	{
		"Name": "No Body Dragging",
		"Type": "Complication",
		"Tip": "Do not drag any NPC bodies. You may grab and box them, provided you do not move while holding onto them.",
		"Group": "Action",
		"Difficulty": "Medium",
		"DragBodyMove": {}
	},
	{
		"Name": "No Body Shots",
		"Type": "Complication",
		"Tip": "Do not shoot any NPC unless it is a headshot.",
		"Group": "Action",
		"Difficulty": "Medium",
		"ProjectileBodyShot": {}
	},
	{
		"Name": "No Climbing Drain Pipes",
		"Type": "Complication",
		"Tip": "Don't climb any drain pipe. This includes vines - anything you can slide down like a pipe. Ladders are okay.",
		"Group": "Action",
		"Difficulty": "Medium",
		"DrainPipeClimbed": {}
	},
	{
		"Name": "No Crouch Running",
		"Type": "Complication",
		"Tip": "Avoid running while crouched.",
		"Group": "Action",
		"Difficulty": "High",
		"Movement": {
			"IsRunning": true,
			"IsCrouching": true
		}
	},
	{
		"Name": "No Crouch Movement",
		"Type": "Complication",
		"Tip": "If you crouch, you must stay still.",
		"Group": "Action",
		"Difficulty": "High",
		"Movement": {
			"IsCrouching": true,
			"OR": [
				{
					"IsRunning": true
				},
				{
					"IsWalking": true
				}
			]
		}
	},
	{
		"Disabled": true,
		"Name": "No Crouch Move in Trespassing",
		"Type": "Complication",
		"Tip": "If you crouch while in trespassing, you must stay still.",
		"Group": "Action",
		"Difficulty": "High",
		"Movement": {
			"IsCrouching": true,
			"IsTrespassing": true,
			"OR": [
				{
					"IsRunning": true
				},
				{
					"IsWalking": true
				}
			]
		}
	},
	{
		"Name": "No Crowd Blending",
		"Type": "Complication",
		"Tip": "Avoid becoming concealed in crowded areas.",
		"Group": "Action",
		"Difficulty": "Medium",
		"OnIsFullyInCrowd": {}
	},
	{
		"Name": "No Damage",
		"Type": "Complication",
		"Tip": "Do not take damage, not even friendly fire.",
		"Group": "Action",
		"Difficulty": "Medium",
		"OnTakeDamage": {}
	},
	{
		"Name": "No Double Doors Opened",
		"Type": "Complication",
		"Tip": "Do not open any double doors by hand.",
		"Group": "Action",
		"Difficulty": "Medium",
		"OpenDoor": {
			"Type": "Double"
		}
	},
	{
		"Name": "No Dropping Items",
		"Type": "Complication",
		"Tip": "Do not drop any item from your hands or inventory. Placing them is fine.",
		"Group": "Action",
		"Difficulty": "Medium",
		"ItemDropped": {}
	},
	{
		"Name": "No Instinct",
		"Type": "Complication",
		"Tip": "Go against your instincts and avoid using instinct.",
		"Group": "Action",
		"Difficulty": "Medium",
		"InstinctActive": {}
	},
	{
		"Disabled": true,
		"Name": "No Pistol Shots",
		"Type": "Complication",
		"Tip": "Do not fire any shots using a pistol.",
		"Group": "Action",
		"Difficulty": "Medium",
		"PlayerShot": {
			"WeaponCategory": "Pistol"
		}
	},
	{
		"Disabled": true,
		"Name": "No SMG Shots",
		"Type": "Complication",
		"Tip": "Do not fire any shots using an SMG.",
		"Group": "Action",
		"Difficulty": "Medium",
		"PlayerShot": {
			"OR": [
				{
					"WeaponCategory": "SMG1H"
				},
				{
					"WeaponCategory": "SMG2H"
				}
			]
		}
	},
	{
		"Disabled": true,
		"Name": "No Shotgun Shots",
		"Type": "Complication",
		"Tip": "Do not fire any shots using a shotgun.",
		"Group": "Action",
		"Difficulty": "Medium",
		"PlayerShot": {
			"OR": [
				{
					"WeaponCategory": "ShotgunPump"
				},
				{
					"WeaponCategory": "ShotgunSemi"
				}
			]
		}
	},
	{
		"Disabled": true,
		"Name": "No Sniper Shots",
		"Type": "Complication",
		"Tip": "Do not fire any shots using an SMG.",
		"Group": "Action",
		"Difficulty": "Medium",
		"PlayerShot": {
			"WeaponCategory": "Sniper"
		}
	},
	{
		"Name": "No Reloading",
		"Type": "Complication",
		"Tip": "Do not reload any weapon. Avoid leaving clips around the place as evidence.",
		"Difficulty": "Medium",
		"OnWeaponReload": {}
	},
	{
		"Name": "No Shots Fired",
		"Type": "Complication",
		"Tip": "Do not fire any shots.",
		"Group": "Action",
		"Difficulty": "Medium",
		"PlayerShot": {}
	},
	{
		"Name": "No Suppressed Shots",
		"Type": "Complication",
		"Tip": "Do not fire any shots using a silenced or subsonic firearm.",
		"Group": "Action",
		"Difficulty": "Medium",
		"PlayerShot": {
			"RepositoryPerks": ["suppressor"]
		}
	},
	{
		"Name": "No Throwing",
		"Type": "Complication",
		"Tip": "Do not throw any item.",
		"Group": "Action",
		"Difficulty": "High",
		"ItemThrown": {}
	},
	{
		"Name": "No Vegetation Concealing",
		"Type": "Complication",
		"Tip": "Avoid concealing yourself in foliage.",
		"Group": "Action",
		"Difficulty": "Medium",
		"OnIsFullyInVegetation": {}
	},
	{
		"Disabled": true,
		"Name": "Only Run Crouched",
		"Type": "Complication",
		"Tip": "Do not run while standing upright, only run while crouching.",
		"Group": "Action",
		"Difficulty": "High",
		"Movement": {
			"IsRunning": true,
			"IsCrouching": false
		}
	}
]